bibim/__init__.py
bibim/__main__.py
bibim/index.py
bibim/reference.py
bibim/search.py
bibim-0.2.1.dist-info/LICENSE
bibim-0.2.1.dist-info/METADATA
bibim-0.2.1.dist-info/WHEEL
bibim-0.2.1.dist-info/entry_points.txt
bibim-0.2.1.dist-info/top_level.txt
bibim-0.2.1.dist-info/RECORD
