Metadata-Version: 2.1
Name: bibim
Version: 0.2.1
Summary: Minimalistic, markdown-based reference manager for computer science research
Home-page: https://github.com/ingim/bibim
Author: In Gim
Author-email: in.gim@yale.edu
Keywords: bibliography bibtex markdown command-line
Classifier: Programming Language :: Python :: 3
Classifier: Intended Audience :: Developers
Classifier: Topic :: Utilities
Classifier: License :: OSI Approved :: MIT License
Classifier: Operating System :: OS Independent
Requires-Python: >=3.8
License-File: LICENSE
Requires-Dist: requests
Requires-Dist: scholarly
Requires-Dist: feedparser
